chat_exporter/__init__.py
chat_exporter/chat_exporter.py
chat_exporter/construct/__init__.py
chat_exporter/construct/attachment_handler.py
chat_exporter/construct/message.py
chat_exporter/construct/transcript.py
chat_exporter/construct/assets/__init__.py
chat_exporter/construct/assets/attachment.py
chat_exporter/construct/assets/component.py
chat_exporter/construct/assets/embed.py
chat_exporter/construct/assets/reaction.py
chat_exporter/ext/__init__.py
chat_exporter/ext/cache.py
chat_exporter/ext/discord_import.py
chat_exporter/ext/discord_utils.py
chat_exporter/ext/discriminator.py
chat_exporter/ext/emoji_convert.py
chat_exporter/ext/html_generator.py
chat_exporter/html/__init__.py
chat_exporter/parse/__init__.py
chat_exporter/parse/markdown.py
chat_exporter/parse/mention.py
sosAl2-0.1.1.dist-info/METADATA
sosAl2-0.1.1.dist-info/WHEEL
sosAl2-0.1.1.dist-info/top_level.txt
sosAl2-0.1.1.dist-info/RECORD
