Metadata-Version: 2.1
Name: sosAl2
Version: 0.1.1
Summary: This is the simplest modu2le for quick work with files.
Author: feeland
Author-email: prokuronov.valera@mail.ru
Keywords: files speedfiles2
Requires-Python: >=3.6
